google_datacatalog_saphana_connector-0.3.0-py3.8-nspkg.pth
google/datacatalog_connectors/saphana/__init__.py
google/datacatalog_connectors/saphana/datacatalog_cli.py
google/datacatalog_connectors/saphana/config/__init__.py
google/datacatalog_connectors/saphana/config/enrich_table_metadata_query.sql
google/datacatalog_connectors/saphana/config/metadata_definition.json
google/datacatalog_connectors/saphana/config/metadata_definition_functions_sql_object.json
google/datacatalog_connectors/saphana/config/metadata_query.sql
google/datacatalog_connectors/saphana/config/query_functions_sql_object.sql
google/datacatalog_connectors/saphana/scrape/__init__.py
google/datacatalog_connectors/saphana/scrape/metadata_scraper.py
google/datacatalog_connectors/saphana/scrape/query_assembler.py
google_datacatalog_saphana_connector-0.3.0.dist-info/METADATA
google_datacatalog_saphana_connector-0.3.0.dist-info/WHEEL
google_datacatalog_saphana_connector-0.3.0.dist-info/entry_points.txt
google_datacatalog_saphana_connector-0.3.0.dist-info/namespace_packages.txt
google_datacatalog_saphana_connector-0.3.0.dist-info/top_level.txt
google_datacatalog_saphana_connector-0.3.0.dist-info/RECORD
