Metadata-Version: 2.1
Name: google-datacatalog-saphana-connector
Version: 0.3.0
Summary: Library for ingesting Sap Hana Database metadata into Google Cloud Data Catalog
Home-page: UNKNOWN
Author: Google LLC
License: UNKNOWN
Platform: Posix; MacOS X; Windows
Classifier: Development Status :: 4 - Beta
Classifier: Programming Language :: Python :: 3.6
Classifier: Programming Language :: Python :: 3.7
Classifier: Programming Language :: Python :: 3.8
Requires-Dist: hdbcli
Requires-Dist: google-datacatalog-rdbms-connector (>=0.12.0<0.13.0)
